fun2py/IO.py
fun2py/__init__.py
fun2py/interface.py
fun2py/type.py
fun2py/utils.py
pyfp/IO.py
pyfp/__init__.py
pyfp/interface.py
pyfp/type.py
pyfp/utils.py
fun2py-0.0.2.dist-info/LICENSE
fun2py-0.0.2.dist-info/METADATA
fun2py-0.0.2.dist-info/WHEEL
fun2py-0.0.2.dist-info/top_level.txt
fun2py-0.0.2.dist-info/RECORD
